adb_mysql_mcp_server/__init__.py
adb_mysql_mcp_server/server.py
mseep_adb_mysql_mcp_server-1.0.4.dist-info/licenses/LICENSE
mseep_adb_mysql_mcp_server-1.0.4.dist-info/METADATA
mseep_adb_mysql_mcp_server-1.0.4.dist-info/WHEEL
mseep_adb_mysql_mcp_server-1.0.4.dist-info/entry_points.txt
mseep_adb_mysql_mcp_server-1.0.4.dist-info/top_level.txt
mseep_adb_mysql_mcp_server-1.0.4.dist-info/RECORD
