Metadata-Version: 2.4
Name: mseep-adb-mysql-mcp-server
Version: 1.0.4
Summary: An offical mcp server for Adb MySQL of Alibaba Cloud
Author-email: mseep <support@skydeck.ai>
Requires-Python: >=3.13
License-File: LICENSE
Requires-Dist: mcp[cli]>=1.5.0
Requires-Dist: pymysql>=1.1.1
Dynamic: license-file
